oidc_validators/__init__.py
oidc_validators/validators.py
oidc_validators-0.5.3.dist-info/LICENSE
oidc_validators-0.5.3.dist-info/METADATA
oidc_validators-0.5.3.dist-info/WHEEL
oidc_validators-0.5.3.dist-info/top_level.txt
oidc_validators-0.5.3.dist-info/RECORD
