Metadata-Version: 2.1
Name: oidc-validators
Version: 0.5.3
Summary: Validates OIDC token
Home-page: http://github.com/unit9/oidc-validators-python
Author: Abirafdi Raditya Putra
Author-email: raditya.putra@unit9.com
License: MIT
Platform: UNKNOWN
Classifier: Development Status :: 5 - Production/Stable
Classifier: Environment :: Web Environment
Classifier: Intended Audience :: Developers
Classifier: License :: OSI Approved :: MIT License
Classifier: Operating System :: OS Independent
Classifier: Programming Language :: Python
Classifier: Programming Language :: Python :: 3
Classifier: Topic :: Internet :: WWW/HTTP
Requires-Python: >=3.7
Requires-Dist: requests
Requires-Dist: cryptography (==2.7)
Requires-Dist: PyJWT (==1.7.1)
